btcontrol/__init__.py
btcontrol/main.py
btcontrol/api/server.py
btcontrol/core/action.py
btcontrol/core/device.py
btcontrol/core/registry.py
btcontrol/discovery/ble.py
btcontrol/discovery/classic.py
btcontrol/drivers/__init__.py
btcontrol/drivers/audio_driver.py
btcontrol/drivers/base.py
btcontrol/drivers/ble_control_driver.py
btcontrol/drivers/ble_standard_driver.py
btcontrol/executors/ble_exec.py
btcontrol/executors/media_exec_windows.py
btcontrol/inference/__init__.py
btcontrol/inference/map.py
btcontrol-0.1.0.dist-info/METADATA
btcontrol-0.1.0.dist-info/WHEEL
btcontrol-0.1.0.dist-info/top_level.txt
btcontrol-0.1.0.dist-info/RECORD
