Metadata-Version: 2.4
Name: btcontrol
Version: 0.1.0
Summary: Driver-based Bluetooth control framework exposing safe device actions via Python and REST API
Author-email: Aditya <iamaditya1866@gmail.com>
License: MIT
Project-URL: Homepage, https://github.com/f1amekaiser/btcontrol
Project-URL: Repository, https://github.com/f1amekaiser/btcontrol
Classifier: Programming Language :: Python :: 3
Classifier: License :: OSI Approved :: MIT License
Classifier: Operating System :: Microsoft :: Windows
Requires-Python: >=3.9
Requires-Dist: bleak
Requires-Dist: fastapi
Requires-Dist: uvicorn
Requires-Dist: keyboard
